{
 "issue": "1.2", 
 "tracks": [
  {
   "background-colour": "red", 
   "background-image": "", 
   "duration": "10", 
   "message-colour": "white", 
   "message-font": "Helvetica 25 bold",
   "message-justify": "left",
   "text": "Demonstrates some of the audio capabilities of Pi Presents\n\nPress down cursor to move through the tracks.\n\nIn case you are wondering:\n*   NTE is an audio magazine for the visually impaired.\n*   Listen at www.ntexpress.org.uk\n*   I am their webmaster.", 
   "title": "Intro", 
   "track-ref": "", 
   "type": "message"
  }, 
  {
   "animate-begin": "", 
   "animate-clear": "no", 
   "animate-end": "", 
   "audio-speaker": "stereo", 
   "background-image": "", 
   "clear-screen": "no", 
   "duration": "0", 
   "location": "+/media/01.mp3", 
   "mplayer-audio": "hdmi", 
   "mplayer-other-options": "", 
   "mplayer-volume": "", 
   "title": "stereo HDMI", 
   "track-ref": "", 
   "track-text": "Playing Audio through HDMI in stereo", 
   "track-text-colour": "white", 
   "track-text-font": "arial 30 bold", 
   "track-text-x": "300", 
   "track-text-y": "100", 
   "type": "audio"
  }, 
  {
   "animate-begin": "", 
   "animate-clear": "no", 
   "animate-end": "", 
   "audio-speaker": "stereo", 
   "background-image": "", 
   "clear-screen": "no", 
   "duration": "0", 
   "location": "+/media/01.mp3", 
   "mplayer-audio": "local", 
   "mplayer-other-options": "", 
   "mplayer-volume": "", 
   "title": "stereo local", 
   "track-ref": "", 
   "track-text": "Through the STEREO headphone socket", 
   "track-text-colour": "yellow", 
   "track-text-font": "arial 30 bold", 
   "track-text-x": "400", 
   "track-text-y": "700", 
   "type": "audio"
  }, 
  {
   "animate-begin": "", 
   "animate-clear": "no", 
   "animate-end": "", 
   "audio-speaker": "left", 
   "background-image": "", 
   "clear-screen": "no", 
   "duration": "0", 
   "location": "+/media/01.mp3", 
   "mplayer-audio": "local", 
   "mplayer-other-options": "", 
   "mplayer-volume": "", 
   "title": "mono left", 
   "track-ref": "", 
   "track-text": "Through the LEFT headphone", 
   "track-text-colour": "green", 
   "track-text-font": "arial 30 bold", 
   "track-text-x": "200", 
   "track-text-y": "200", 
   "type": "audio"
  }, 
  {
   "animate-begin": "", 
   "animate-clear": "no", 
   "animate-end": "", 
   "audio-speaker": "right", 
   "background-image": "+/media/sarename.gif", 
   "clear-screen": "no", 
   "duration": "0", 
   "location": "+/media/01.mp3", 
   "mplayer-audio": "local", 
   "mplayer-other-options": "", 
   "mplayer-volume": "", 
   "title": "right local", 
   "track-ref": "", 
   "track-text": "Through the RIGHT headphone socket", 
   "track-text-colour": "pink", 
   "track-text-font": "arial 20 bold", 
   "track-text-x": "600", 
   "track-text-y": "700", 
   "type": "audio"
  }
 ]
}